tiny_algos/__init__.py
tiny_algos/minmultiset.py
tiny_algos/mod_arithmetic.py
tiny_algos/multiset.py
tiny_algos-0.1.1.dist-info/LICENSE.md
tiny_algos-0.1.1.dist-info/WHEEL
tiny_algos-0.1.1.dist-info/METADATA
tiny_algos-0.1.1.dist-info/RECORD
