Metadata-Version: 2.1
Name: tiny-algos
Version: 0.1.1
Summary: A compact modules for Data Structures and Algorithms
License: MIT
Author: azriel1rf
Author-email: azriel.1rf@gmail.com
Requires-Python: >=3.9,<4.0
Classifier: License :: OSI Approved :: MIT License
Classifier: Programming Language :: Python :: 3
Classifier: Programming Language :: Python :: 3.10
Classifier: Programming Language :: Python :: 3.9
